choropleth_geojson/__init__.py
choropleth_geojson-0.0.7.dist-info/METADATA
choropleth_geojson-0.0.7.dist-info/RECORD
choropleth_geojson-0.0.7.dist-info/WHEEL
choropleth_geojson-0.0.7.dist-info/top_level.txt
