Metadata-Version: 2.1
Name: choropleth-geojson
Version: 0.0.7
Summary: Plot a choropleth map with a geojson file.
Home-page: https://github.com/QuantStats/choropleth_geojson
Author: Wei Ruen Leong
Author-email: wei.leong2@uqconnect.edu.au
License: UNKNOWN
Platform: UNKNOWN
Classifier: License :: OSI Approved :: MIT License
Classifier: Programming Language :: Python :: 3
Classifier: Operating System :: OS Independent
Classifier: Intended Audience :: Science/Research
Classifier: Topic :: Scientific/Engineering :: Visualization
